COPYING
MANIFEST.in
README.md
setup.py
mosaicode_lib_c_opencv/__init__.py
mosaicode_lib_c_opencv.egg-info/PKG-INFO
mosaicode_lib_c_opencv.egg-info/SOURCES.txt
mosaicode_lib_c_opencv.egg-info/dependency_links.txt
mosaicode_lib_c_opencv.egg-info/requires.txt
mosaicode_lib_c_opencv.egg-info/top_level.txt
mosaicode_lib_c_opencv/extensions/__init__.py
mosaicode_lib_c_opencv/extensions/cfile.py
mosaicode_lib_c_opencv/extensions/opencv/__init__.py
mosaicode_lib_c_opencv/extensions/opencv/Arithmetic and Logical Operations/__init__.py
mosaicode_lib_c_opencv/extensions/opencv/Arithmetic and Logical Operations/and.py
mosaicode_lib_c_opencv/extensions/opencv/Arithmetic and Logical Operations/division.py
mosaicode_lib_c_opencv/extensions/opencv/Arithmetic and Logical Operations/multiplication.py
mosaicode_lib_c_opencv/extensions/opencv/Arithmetic and Logical Operations/not.py
mosaicode_lib_c_opencv/extensions/opencv/Arithmetic and Logical Operations/or.py
mosaicode_lib_c_opencv/extensions/opencv/Arithmetic and Logical Operations/sidebyside.py
mosaicode_lib_c_opencv/extensions/opencv/Arithmetic and Logical Operations/subtraction.py
mosaicode_lib_c_opencv/extensions/opencv/Arithmetic and Logical Operations/sum.py
mosaicode_lib_c_opencv/extensions/opencv/Arithmetic and Logical Operations/uptobottom.py
mosaicode_lib_c_opencv/extensions/opencv/Arithmetic and Logical Operations/xor.py
mosaicode_lib_c_opencv/extensions/opencv/Basic Data Type/__init__.py
mosaicode_lib_c_opencv/extensions/opencv/Basic Data Type/newDouble.py
mosaicode_lib_c_opencv/extensions/opencv/Basic Data Type/newInt.py
mosaicode_lib_c_opencv/extensions/opencv/Basic Data Type/newPoint.py
mosaicode_lib_c_opencv/extensions/opencv/Basic Data Type/newRect.py
mosaicode_lib_c_opencv/extensions/opencv/Basic Data Type/slider.py
mosaicode_lib_c_opencv/extensions/opencv/Basic Shapes/__init__.py
mosaicode_lib_c_opencv/extensions/opencv/Basic Shapes/circle.py
mosaicode_lib_c_opencv/extensions/opencv/Basic Shapes/fillRect.py
mosaicode_lib_c_opencv/extensions/opencv/Experimental/__init__.py
mosaicode_lib_c_opencv/extensions/opencv/Experimental/addborder.py
mosaicode_lib_c_opencv/extensions/opencv/Experimental/cropImage.py
